cloe_etl_adf/__init__.py
cloe_etl_adf/azure_resources.py
cloe_etl_adf/main.py
cloe_etl_adf/py.typed
cloe_etl_adf/factory_objects/__init__.py
cloe_etl_adf/factory_objects/execute_pipeline_activity.py
cloe_etl_adf/factory_objects/pipeline_resource.py
cloe_etl_adf/factory_objects/trigger.py
cloe_etl_adf/job_packages/__init__.py
cloe_etl_adf/job_packages/db2fs.py
cloe_etl_adf/job_packages/exec_sql.py
cloe_etl_adf/job_packages/fs2db.py
cloe_etl_adf/utils/__init__.py
cloe_etl_adf/utils/create_pipelines.py
cloe_etl_adf/utils/factory.py
cloe_etl_adf/utils/load_models.py
cloe_etl_adf/utils/pipelines.py
cloe_etl_adf-1.0.10.dist-info/METADATA
cloe_etl_adf-1.0.10.dist-info/WHEEL
cloe_etl_adf-1.0.10.dist-info/entry_points.txt
cloe_etl_adf-1.0.10.dist-info/RECORD
