Metadata-Version: 2.4
Name: cloe-etl-adf
Version: 1.0.10
Summary: Generates the orchestration pipelines for the job template package based on metadata.
Author-email: initions <ICSMC_EXT_PYPIORG@accenture.com>
License: MIT
Classifier: Development Status :: 5 - Production/Stable
Classifier: Environment :: Console
Classifier: Intended Audience :: Developers
Classifier: License :: OSI Approved :: MIT License
Classifier: Operating System :: OS Independent
Classifier: Programming Language :: Python :: 3
Classifier: Topic :: Database
Requires-Python: <3.12,>=3.11
Requires-Dist: cloe-metadata-to-ddl~=1.1.5
Requires-Dist: cloe-metadata~=2.2.4
Requires-Dist: pydantic~=2.11.7
Requires-Dist: typer[all]~=0.16.0
